spiky/__init__.py
spiky/spiky.py
spiky/toolbox.py
spiky-1.0.4.dist-info/DESCRIPTION.rst
spiky-1.0.4.dist-info/METADATA
spiky-1.0.4.dist-info/RECORD
spiky-1.0.4.dist-info/WHEEL
spiky-1.0.4.dist-info/metadata.json
spiky-1.0.4.dist-info/top_level.txt
