Metadata-Version: 2.0
Name: spiky
Version: 1.0.4
Summary: Spike sorting based on Gaussian Mixture Model
Home-page: https://github.com/rodriguez-facundo/spiky
Author: F. Rodriguez
Author-email: frodriguez4600@gmail.com
License: UNKNOWN
Keywords: spike sorting
Platform: UNKNOWN
Classifier: Development Status :: 4 - Beta
Classifier: Intended Audience :: Science/Research
Classifier: Topic :: Scientific/Engineering :: Medical Science Apps.
Classifier: License :: OSI Approved :: MIT License
Classifier: Programming Language :: Python :: 3.6
Requires-Dist: numpy
Requires-Dist: matplotlib
Requires-Dist: progressbar2
Requires-Dist: pywavelets
Requires-Dist: scipy
Requires-Dist: sklearn
